[
  {"product_name": "4070", "search_count": 1},
  {"product_name": "4080", "search_count": 12},
  {"product_name": "4090", "search_count": 15},
  {"product_name": "i5 12400f", "search_count": 10},
  {"product_name": "i7 13700k", "search_count": 18},
  {"product_name": "Ryzen 5 5600", "search_count": 14},
  {"product_name": "Ryzen 7 5800X", "search_count": 11},
  {"product_name": "B550 motherboard", "search_count": 8},
  {"product_name": "Z690 motherboard", "search_count": 6},
  {"product_name": "DDR5 RAM 32GB", "search_count": 13},
  {"product_name": "750W PSU", "search_count": 9},
  {"product_name": "1000W PSU", "search_count": 7},
  {"product_name": "RTX 4060", "search_count": 4},
  {"product_name": "RTX 4070 Ti", "search_count": 16},
  {"product_name": "Samsung 980 Pro 1TB", "search_count": 5},
  {"product_name": "Crucial P3 500GB", "search_count": 3},
  {"product_name": "Lian Li O11", "search_count": 6},
  {"product_name": "NZXT H510", "search_count": 2},
  {"product_name": "Noctua NH-D15", "search_count": 4},
  {"product_name": "DeepCool AK620", "search_count": 3}
]